[{"asset":"ADA","signal":"DOWN","delta":"-0.2626%","size_usd":2,"entry_price":0.1899,"exit_price":0.1902,"status":"lost","pnl_usdc":-0.0072,"mode":"PAPER","created_at":"2026-07-05T18:17:02.023636+00:00"}, 
 {"asset":"BNB","signal":"DOWN","delta":"-0.2105%","size_usd":2,"entry_price":583.18,"exit_price":585.37,"status":"lost","pnl_usdc":-0.0115,"mode":"PAPER","created_at":"2026-07-05T18:33:02.082553+00:00"}, 
 {"asset":"ADA","signal":"DOWN","delta":"-0.2103%","size_usd":2,"entry_price":0.1898,"exit_price":0.1898,"status":"lost","pnl_usdc":-0.0040,"mode":"PAPER","created_at":"2026-07-05T18:45:02.596684+00:00"}, 
 {"asset":"BNB","signal":"UP","delta":"+0.4013%","size_usd":2,"entry_price":590.49,"exit_price":590.38,"status":"lost","pnl_usdc":-0.0044,"mode":"PAPER","created_at":"2026-07-05T19:05:02.282651+00:00"}, 
 {"asset":"SOL","signal":"DOWN","delta":"-0.2094%","size_usd":2,"entry_price":81.03,"exit_price":80.97,"status":"lost","pnl_usdc":-0.0025,"mode":"PAPER","created_at":"2026-07-05T19:11:02.071303+00:00"}, 
 {"asset":"ADA","signal":"DOWN","delta":"-0.2102%","size_usd":2,"entry_price":0.1899,"exit_price":0.1898,"status":"lost","pnl_usdc":-0.0029,"mode":"PAPER","created_at":"2026-07-05T19:11:02.393924+00:00"}, 
 {"asset":"ETH","signal":"DOWN","delta":"-0.2181%","size_usd":2,"entry_price":1779.9,"exit_price":1782.79,"status":"lost","pnl_usdc":-0.0072,"mode":"PAPER","created_at":"2026-07-05T19:13:02.032279+00:00"}, 
 {"asset":"XRP","signal":"DOWN","delta":"-0.2111%","size_usd":2,"entry_price":1.1343,"exit_price":1.1365,"status":"lost","pnl_usdc":-0.0079,"mode":"PAPER","created_at":"2026-07-05T19:17:02.036868+00:00"}, 
 {"asset":"DOGE","signal":"DOWN","delta":"-0.2060%","size_usd":2,"entry_price":0.07752,"exit_price":0.07737,"status":"lost","pnl_usdc":-0.0001,"mode":"PAPER","created_at":"2026-07-05T19:22:02.097549+00:00"}, 
 {"asset":"ADA","signal":"DOWN","delta":"-0.2104%","size_usd":2,"entry_price":0.1897,"exit_price":0.1892,"status":"won","pnl_usdc":0.0013,"mode":"PAPER","created_at":"2026-07-05T19:34:02.311362+00:00"}, 
 {"asset":"ETH","signal":"DOWN","delta":"-0.2341%","size_usd":2,"entry_price":1776.97,"exit_price":1780.8,"status":"lost","pnl_usdc":-0.0083,"mode":"PAPER","created_at":"2026-07-05T19:41:02.15061+00:00"}, 
 {"asset":"DOGE","signal":"DOWN","delta":"-0.2068%","size_usd":2,"entry_price":0.0772,"exit_price":0.07732,"status":"lost","pnl_usdc":-0.0071,"mode":"PAPER","created_at":"2026-07-05T19:41:02.634792+00:00"}, 
 {"asset":"ADA","signal":"DOWN","delta":"-0.2114%","size_usd":2,"entry_price":0.1888,"exit_price":0.1889,"status":"lost","pnl_usdc":-0.0051,"mode":"PAPER","created_at":"2026-07-05T19:59:02.035377+00:00"}, 
 {"asset":"BNB","signal":"DOWN","delta":"-0.2103%","size_usd":2,"entry_price":588.46,"exit_price":587.94,"status":"lost","pnl_usdc":-0.0022,"mode":"PAPER","created_at":"2026-07-05T20:35:02.825803+00:00"}, 
 {"asset":"ADA","signal":"DOWN","delta":"-0.2655%","size_usd":2,"entry_price":0.1878,"exit_price":0.1884,"status":"lost","pnl_usdc":-0.0104,"mode":"PAPER","created_at":"2026-07-05T20:54:02.14667+00:00"}, 
 {"asset":"ETH","signal":"DOWN","delta":"-0.2122%","size_usd":2,"entry_price":1772.53,"exit_price":1772.4,"status":"lost","pnl_usdc":-0.0039,"mode":"PAPER","created_at":"2026-07-05T21:17:02.028116+00:00"}, 
 {"asset":"LINK","signal":"DOWN","delta":"-0.2000%","size_usd":2,"entry_price":7.984,"exit_price":7.984,"status":"lost","pnl_usdc":-0.0040,"mode":"PAPER","created_at":"2026-07-05T21:17:02.214864+00:00"}, 
 {"asset":"ADA","signal":"DOWN","delta":"-0.2122%","size_usd":2,"entry_price":0.1881,"exit_price":0.1883,"status":"lost","pnl_usdc":-0.0061,"mode":"PAPER","created_at":"2026-07-05T21:18:02.039303+00:00"}, 
 {"asset":"SOL","signal":"DOWN","delta":"-0.2224%","size_usd":2,"entry_price":80.77,"exit_price":81.18,"status":"lost","pnl_usdc":-0.0142,"mode":"PAPER","created_at":"2026-07-05T21:19:02.167377+00:00"}, 
 {"asset":"SOL","signal":"UP","delta":"+0.3337%","size_usd":2,"entry_price":81.18,"exit_price":81.61,"status":"won","pnl_usdc":0.0066,"mode":"PAPER","created_at":"2026-07-05T21:32:02.17234+00:00"}, 
 {"asset":"XRP","signal":"UP","delta":"+0.3614%","size_usd":2,"entry_price":1.1386,"exit_price":1.1428,"status":"won","pnl_usdc":0.0034,"mode":"PAPER","created_at":"2026-07-05T21:35:02.026152+00:00"}, 
 {"asset":"DOGE","signal":"UP","delta":"+0.3893%","size_usd":2,"entry_price":0.07737,"exit_price":0.07754,"status":"won","pnl_usdc":0.0004,"mode":"PAPER","created_at":"2026-07-05T21:35:02.494152+00:00"}, 
 {"asset":"ADA","signal":"UP","delta":"+0.3725%","size_usd":2,"entry_price":0.1886,"exit_price":0.1889,"status":"lost","pnl_usdc":-0.0008,"mode":"PAPER","created_at":"2026-07-05T21:35:02.826632+00:00"}, 
 {"asset":"LINK","signal":"UP","delta":"+0.3370%","size_usd":2,"entry_price":8.04,"exit_price":8.027,"status":"lost","pnl_usdc":-0.0072,"mode":"PAPER","created_at":"2026-07-05T21:46:02.116954+00:00"}, 
 {"asset":"SOL","signal":"DOWN","delta":"-0.2201%","size_usd":2,"entry_price":81.64,"exit_price":81.52,"status":"lost","pnl_usdc":-0.0011,"mode":"PAPER","created_at":"2026-07-05T21:48:02.062944+00:00"}, 
 {"asset":"BNB","signal":"DOWN","delta":"-0.2088%","size_usd":2,"entry_price":587.72,"exit_price":588.47,"status":"lost","pnl_usdc":-0.0066,"mode":"PAPER","created_at":"2026-07-05T21:51:02.09152+00:00"}, 
 {"asset":"XRP","signal":"DOWN","delta":"-0.2098%","size_usd":2,"entry_price":1.1413,"exit_price":1.1424,"status":"lost","pnl_usdc":-0.0059,"mode":"PAPER","created_at":"2026-07-05T21:51:02.25877+00:00"}, 
 {"asset":"ADA","signal":"UP","delta":"+0.3692%","size_usd":2,"entry_price":0.1903,"exit_price":0.1907,"status":"won","pnl_usdc":0.0002,"mode":"PAPER","created_at":"2026-07-05T21:52:17.152662+00:00"}, 
 {"asset":"ADA","signal":"DOWN","delta":"-0.3136%","size_usd":2,"entry_price":0.1907,"exit_price":0.1911,"status":"lost","pnl_usdc":-0.0082,"mode":"PAPER","created_at":"2026-07-05T21:56:47.197088+00:00"}, 
 {"asset":"ADA","signal":"UP","delta":"+0.3676%","size_usd":2,"entry_price":0.1911,"exit_price":0.1905,"status":"lost","pnl_usdc":-0.0103,"mode":"PAPER","created_at":"2026-07-05T21:58:47.166079+00:00"}, 
 {"asset":"LINK","signal":"UP","delta":"+0.4985%","size_usd":2,"entry_price":8.064,"exit_price":8.052,"status":"lost","pnl_usdc":-0.0070,"mode":"PAPER","created_at":"2026-07-05T21:59:02.147825+00:00"}, 
 {"asset":"ETH","signal":"UP","delta":"+0.3415%","size_usd":2,"entry_price":1786.66,"exit_price":1786.64,"status":"lost","pnl_usdc":-0.0040,"mode":"PAPER","created_at":"2026-07-05T21:59:17.18558+00:00"}, 
 {"asset":"DOGE","signal":"UP","delta":"+0.3872%","size_usd":2,"entry_price":0.07777,"exit_price":0.07795,"status":"won","pnl_usdc":0.0006,"mode":"PAPER","created_at":"2026-07-05T21:59:32.104555+00:00"}, 
 {"asset":"XRP","signal":"UP","delta":"+0.4289%","size_usd":2,"entry_price":1.1473,"exit_price":1.1444,"status":"lost","pnl_usdc":-0.0091,"mode":"PAPER","created_at":"2026-07-05T21:59:47.107721+00:00"}, 
 {"asset":"SOL","signal":"UP","delta":"+0.3437%","size_usd":2,"entry_price":81.75,"exit_price":81.66,"status":"lost","pnl_usdc":-0.0062,"mode":"PAPER","created_at":"2026-07-05T22:00:17.119263+00:00"}, 
 {"asset":"BNB","signal":"UP","delta":"+0.4163%","size_usd":2,"entry_price":590.9,"exit_price":588.96,"status":"lost","pnl_usdc":-0.0106,"mode":"PAPER","created_at":"2026-07-05T22:00:32.111386+00:00"}, 
 {"asset":"SOL","signal":"DOWN","delta":"-0.2199%","size_usd":2,"entry_price":81.66,"exit_price":81.96,"status":"lost","pnl_usdc":-0.0113,"mode":"PAPER","created_at":"2026-07-05T22:03:17.162607+00:00"}, 
 {"asset":"XRP","signal":"DOWN","delta":"-0.2180%","size_usd":2,"entry_price":1.1444,"exit_price":1.1462,"status":"lost","pnl_usdc":-0.0071,"mode":"PAPER","created_at":"2026-07-05T22:03:32.255404+00:00"}, 
 {"asset":"DOGE","signal":"DOWN","delta":"-0.2048%","size_usd":2,"entry_price":0.07795,"exit_price":0.07801,"status":"lost","pnl_usdc":-0.0055,"mode":"PAPER","created_at":"2026-07-05T22:03:32.461525+00:00"}, 
 {"asset":"LINK","signal":"DOWN","delta":"-0.2230%","size_usd":2,"entry_price":8.052,"exit_price":8.068,"status":"lost","pnl_usdc":-0.0080,"mode":"PAPER","created_at":"2026-07-05T22:03:32.69771+00:00"}, 
 {"asset":"SOL","signal":"UP","delta":"+0.3551%","size_usd":2,"entry_price":81.96,"exit_price":81.77,"status":"lost","pnl_usdc":-0.0086,"mode":"PAPER","created_at":"2026-07-05T22:04:17.111926+00:00"}, 
 {"asset":"XRP","signal":"UP","delta":"+0.3502%","size_usd":2,"entry_price":1.1462,"exit_price":1.1436,"status":"lost","pnl_usdc":-0.0085,"mode":"PAPER","created_at":"2026-07-05T22:04:32.175104+00:00"}, 
 {"asset":"DOGE","signal":"UP","delta":"+0.3344%","size_usd":2,"entry_price":0.07801,"exit_price":0.07778,"status":"lost","pnl_usdc":-0.0099,"mode":"PAPER","created_at":"2026-07-05T22:04:32.355125+00:00"}, 
 {"asset":"ADA","signal":"DOWN","delta":"-0.2095%","size_usd":2,"entry_price":0.1905,"exit_price":0.1901,"status":"won","pnl_usdc":0.0002,"mode":"PAPER","created_at":"2026-07-05T22:14:02.10469+00:00"}, 
 {"asset":"ETH","signal":"DOWN","delta":"-0.2568%","size_usd":2,"entry_price":1786.64,"exit_price":1791.43,"status":"lost","pnl_usdc":-0.0094,"mode":"PAPER","created_at":"2026-07-05T22:15:04.591465+00:00"}, 
 {"asset":"BNB","signal":"DOWN","delta":"-0.2557%","size_usd":2,"entry_price":588.96,"exit_price":589.83,"status":"lost","pnl_usdc":-0.0070,"mode":"PAPER","created_at":"2026-07-05T22:16:02.105185+00:00"}, 
 {"asset":"XRP","signal":"DOWN","delta":"-0.2355%","size_usd":2,"entry_price":1.1436,"exit_price":1.1516,"status":"lost","pnl_usdc":-0.0180,"mode":"PAPER","created_at":"2026-07-05T22:17:17.129771+00:00"}]